{
  "version": 1,
  "chain": "slot",
  "accountAddress": "0x127fd5f1fe78a71f8bcd1fec63e3fe2f0486b6ecd5c86a0466c3a21fa5cfcec",
  "owner": {
    "environment": "slot.blitz",
    "gameName": "bltz-blink-120",
    "launchRequestId": "23261304987-1",
    "workflowName": "Game Launch",
    "workflowRunId": 23261304987,
    "workflowRunAttempt": 1,
    "stepId": "grant-lootchest-role",
    "leaseId": "43d7f2a5-c472-40e0-9e70-e9c5904d639a"
  },
  "acquiredAt": "2026-03-18T18:46:38.036Z",
  "heartbeatAt": "2026-03-18T18:46:40.961Z",
  "expiresAt": "2026-03-18T18:46:40.961Z",
  "releasedAt": "2026-03-18T18:46:40.961Z"
}
