{
  "version": 1,
  "chain": "mainnet",
  "accountAddress": "0x023003676EF4A5E8f32f5c8714f83fc6bfbefD44C0461a8b7Be16d05b8Ea1532",
  "owner": {
    "environment": "mainnet.blitz",
    "gameName": "bltz-warzone",
    "launchRequestId": "23693806890-1",
    "workflowName": "Game Launch",
    "workflowRunId": 23693806890,
    "workflowRunAttempt": 1,
    "stepId": "create-world",
    "leaseId": "e15b8cfa-61b5-4f4c-b208-6a4f8568a44b"
  },
  "acquiredAt": "2026-03-28T20:37:11.867Z",
  "heartbeatAt": "2026-03-28T20:37:11.867Z",
  "expiresAt": "2026-03-28T20:47:11.867Z"
}
