{
  "version": 1,
  "chain": "mainnet",
  "accountAddress": "0x023003676EF4A5E8f32f5c8714f83fc6bfbefD44C0461a8b7Be16d05b8Ea1532",
  "owner": {
    "environment": "mainnet.blitz",
    "gameName": "bltz-warzone",
    "launchRequestId": "23696191041-1",
    "workflowName": "Game Launch",
    "workflowRunId": 23696191041,
    "workflowRunAttempt": 1,
    "stepId": "grant-lootchest-role",
    "leaseId": "4e19a9ba-4864-4353-84a1-be3e3403da9a"
  },
  "acquiredAt": "2026-03-28T22:58:15.341Z",
  "heartbeatAt": "2026-03-28T22:58:15.341Z",
  "expiresAt": "2026-03-28T23:08:15.341Z"
}
