{
  "version": 1,
  "chain": "mainnet",
  "accountAddress": "0x023003676EF4A5E8f32f5c8714f83fc6bfbefD44C0461a8b7Be16d05b8Ea1532",
  "owner": {
    "environment": "mainnet.blitz",
    "gameName": "bltz-battle",
    "launchRequestId": "23897015671-1",
    "workflowName": "Game Launch",
    "workflowRunId": 23897015671,
    "workflowRunAttempt": 1,
    "stepId": "grant-lootchest-role",
    "leaseId": "c2e8fa86-119e-47f6-aa11-76b856e7d733"
  },
  "acquiredAt": "2026-04-02T10:57:41.723Z",
  "heartbeatAt": "2026-04-02T10:57:41.723Z",
  "expiresAt": "2026-04-02T11:07:41.723Z"
}
