{
  "version": 1,
  "chain": "mainnet",
  "accountAddress": "0x023003676EF4A5E8f32f5c8714f83fc6bfbefD44C0461a8b7Be16d05b8Ea1532",
  "owner": {
    "environment": "mainnet.blitz",
    "gameName": "bltz-warzone",
    "launchRequestId": "23679545696-1",
    "workflowName": "Game Launch",
    "workflowRunId": 23679545696,
    "workflowRunAttempt": 1,
    "stepId": "create-world",
    "leaseId": "41630a22-6a97-4fa1-8f77-e4b3f8d789f2"
  },
  "acquiredAt": "2026-03-28T06:41:56.701Z",
  "heartbeatAt": "2026-03-28T06:41:56.701Z",
  "expiresAt": "2026-03-28T06:51:56.701Z"
}
