{
  "version": 1,
  "chain": "mainnet",
  "accountAddress": "0x023003676EF4A5E8f32f5c8714f83fc6bfbefD44C0461a8b7Be16d05b8Ea1532",
  "owner": {
    "environment": "mainnet.blitz",
    "gameName": "bltz-warzone",
    "launchRequestId": "23813483692-1",
    "workflowName": "Game Launch",
    "workflowRunId": 23813483692,
    "workflowRunAttempt": 1,
    "stepId": "create-world",
    "leaseId": "9e9ec3f6-4f3b-4ebc-9359-5d183b08c42a"
  },
  "acquiredAt": "2026-03-31T18:37:12.108Z",
  "heartbeatAt": "2026-03-31T18:37:12.108Z",
  "expiresAt": "2026-03-31T18:47:12.108Z"
}
