{
  "version": 1,
  "chain": "mainnet",
  "accountAddress": "0x023003676EF4A5E8f32f5c8714f83fc6bfbefD44C0461a8b7Be16d05b8Ea1532",
  "owner": {
    "environment": "mainnet.blitz",
    "gameName": "bltz-battle",
    "launchRequestId": "23880300509-1",
    "workflowName": "Game Launch",
    "workflowRunId": 23880300509,
    "workflowRunAttempt": 1,
    "stepId": "grant-lootchest-role",
    "leaseId": "191e850a-9002-4c8e-9dfa-d17c35285e87"
  },
  "acquiredAt": "2026-04-02T02:13:00.762Z",
  "heartbeatAt": "2026-04-02T02:13:00.762Z",
  "expiresAt": "2026-04-02T02:23:00.762Z"
}
